nat/meta/pypi.md
nat/plugins/mcp/__init__.py
nat/plugins/mcp/client_base.py
nat/plugins/mcp/client_config.py
nat/plugins/mcp/client_impl.py
nat/plugins/mcp/exception_handler.py
nat/plugins/mcp/exceptions.py
nat/plugins/mcp/register.py
nat/plugins/mcp/tool.py
nat/plugins/mcp/utils.py
nat/plugins/mcp/auth/__init__.py
nat/plugins/mcp/auth/auth_flow_handler.py
nat/plugins/mcp/auth/auth_provider.py
nat/plugins/mcp/auth/auth_provider_config.py
nat/plugins/mcp/auth/register.py
nat/plugins/mcp/auth/token_storage.py
nvidia_nat_mcp-1.3.1.dist-info/licenses/LICENSE-3rd-party.txt
nvidia_nat_mcp-1.3.1.dist-info/licenses/LICENSE.md
nvidia_nat_mcp-1.3.1.dist-info/METADATA
nvidia_nat_mcp-1.3.1.dist-info/WHEEL
nvidia_nat_mcp-1.3.1.dist-info/entry_points.txt
nvidia_nat_mcp-1.3.1.dist-info/top_level.txt
nvidia_nat_mcp-1.3.1.dist-info/RECORD
